[{"tweet_id": "1467811795", "date": "04-06-2009", "username": "USERID_1", "num_liked": 7791, "tweet_text": "@Tatiana_K nope they didn't have it ", "is_retweet": "False"}, {"tweet_id": "1467812025", "date": "04-06-2009", "username": "USERID_1", "num_liked": 8149, "tweet_text": "@twittera que me muera ? ", "is_retweet": "False"}, {"tweet_id": "1467813579", "date": "04-06-2009", "username": "USERID_1", "num_liked": 1348, "tweet_text": "@LettyA ahh ive always wanted to see rent  love the soundtrack!!", "is_retweet": "True"}, {"tweet_id": "1467813782", "date": "04-06-2009", "username": "USERID_1", "num_liked": 4770, "tweet_text": "@FakerPattyPattz Oh dear. Were you drinking out of the forgotten table drinks? ", "is_retweet": "True"}, {"tweet_id": "1467812579", "date": "04-06-2009", "username": "USERID_1", "tweet_text": "I just re-pierced my ears ", "is_retweet": false, "num_liked": 9700}, {"tweet_id": "1467812964", "date": "04-06-2009", "username": "USERID_10", "num_liked": 3684, "tweet_text": "Hollis' death scene will hurt me severely to watch on film  wry is directors cut not out now?", "is_retweet": "True"}, {"tweet_id": "1467812784", "date": "04-06-2009", "username": "USERID_10", "tweet_text": "@smarrison i would've been the first, but i didn't have a gun.    not really though, zac snyder's just a doucheclown.", "is_retweet": true, "num_liked": 2667}, {"tweet_id": "1467812723", "date": "04-06-2009", "username": "USERID_3", "tweet_text": "@caregiving I couldn't bear to watch it.  And I thought the UA loss was embarrassing . . . . .", "is_retweet": true, "num_liked": 5414}, {"tweet_id": "1467810369", "date": "04-06-2009", "username": "USERID_4", "tweet_text": "@switchfoot http://twitpic.com/2y1zl - Awww, that's a bummer.  You shoulda got David Carr of Third Day to do it. ;D", "is_retweet": false, "num_liked": 315}, {"tweet_id": "1467813137", "date": "04-06-2009", "username": "USERID_5", "num_liked": 6816, "tweet_text": "about to file taxes ", "is_retweet": "False"}, {"tweet_id": "1467811372", "date": "04-06-2009", "username": "USERID_6", "num_liked": 5882, "tweet_text": "@Kwesidei not the whole crew ", "is_retweet": "True"}, {"tweet_id": "1467811184", "date": "04-06-2009", "username": "USERID_6", "tweet_text": "my whole body feels itchy and like its on fire ", "is_retweet": true, "num_liked": 2650}, {"tweet_id": "1467812799", "date": "04-06-2009", "username": "USERID_7", "num_liked": 3340, "tweet_text": "@iamjazzyfizzle I wish I got to watch it with you!! I miss you and @iamlilnicki  how was the premiere?!", "is_retweet": "False"}, {"tweet_id": "1467811592", "date": "04-06-2009", "username": "USERID_8", "num_liked": 2676, "tweet_text": "Need a hug ", "is_retweet": "True"}, {"tweet_id": "1467810672", "date": "04-06-2009", "username": "USERID_8", "tweet_text": "is upset that he can't update his Facebook by texting it... and might cry as a result  School today also. Blah!", "is_retweet": true, "num_liked": 5298}, {"tweet_id": "1467810917", "date": "04-06-2009", "username": "USERID_8", "tweet_text": "@Kenichan I dived many times for the ball. Managed to save 50%  The rest go out of bounds", "is_retweet": true, "num_liked": 533}, {"tweet_id": "1467811193", "date": "04-06-2009", "username": "USERID_8", "tweet_text": "@nationwideclass no, it's not behaving at all. i'm mad. why am i here? because I can't see you all over there. ", "is_retweet": false, "num_liked": 2101}, {"tweet_id": "1467812771", "date": "04-06-2009", "username": "USERID_8", "tweet_text": "@octolinz16 It it counts, idk why I did either. you never talk to me anymore ", "is_retweet": false, "num_liked": 2190}, {"tweet_id": "1467811594", "date": "04-06-2009", "username": "USERID_9", "num_liked": 2182, "tweet_text": "@LOLTrish hey  long time no see! Yes.. Rains a bit ,only a bit  LOL , I'm fine thanks , how's you ?", "is_retweet": "True"}, {"tweet_id": "1467812416", "date": "04-06-2009", "username": "USERID_9", "tweet_text": "spring break in plain city... it's snowing ", "is_retweet": false, "num_liked": 5278}]